.coveragerc
.gitignore
.travis.yml
.travis_orig.yml
AUTHORS.rst
CHANGELOG.rst
LICENSE.txt
MANIFEST.in
README.rst
TODO.md
requirements.txt
setup.cfg
setup.py
tmp.py
tox.ini
docs/Makefile
docs/authors.rst
docs/changelog.rst
docs/conf.py
docs/index.rst
docs/license.rst
docs/_static/.gitignore
examples/apiconfig.py
examples/plotly_example.py
examples/seaborn_example.py
examples/timezone.py
src/speedtest_reader/__init__.py
src/speedtest_reader/cmdltest.py
src/speedtest_reader/oldinit.py
src/speedtest_reader/reader.py
src/speedtest_reader/util.py
src/speedtest_reader.egg-info/PKG-INFO
src/speedtest_reader.egg-info/SOURCES.txt
src/speedtest_reader.egg-info/dependency_links.txt
src/speedtest_reader.egg-info/entry_points.txt
src/speedtest_reader.egg-info/not-zip-safe
src/speedtest_reader.egg-info/requires.txt
src/speedtest_reader.egg-info/top_level.txt
testdata/guam.csv
testdata/headers+1.csv
testdata/random.file
testdata/speedtest.json
tests/conftest.py
tests/helpers.py
tests/test_Reader.py
tests/test_decorators.py
tests/test_formatter.py
tests/test_mnemonics.py
tests/travis_install_orig.sh