Metadata-Version: 2.1
Name: speedtest-reader
Version: 0.0.4
Summary: Selectively read file output generated by speedtest-cli
Home-page: https://github.com/shuntingyard/speedtest_reader
Author: Tobias Frei
Author-email: shuntingard@gmail.com
License: mit
Platform: any
Classifier: Development Status :: 4 - Beta
Classifier: Programming Language :: Python
Classifier: Intended Audience :: Developers
Classifier: License :: OSI Approved :: MIT License
Classifier: Operating System :: OS Independent
Classifier: Programming Language :: Python :: 3 :: Only
Classifier: Topic :: Internet :: Log Analysis
Classifier: Topic :: System :: Networking
Classifier: Topic :: System :: Networking :: Monitoring
Requires-Python: >=3.*
Provides-Extra: testing
